snib/__init__.py
snib/__main__.py
snib/chunker.py
snib/cli.py
snib/config.py
snib/formatter.py
snib/logger.py
snib/models.py
snib/pipeline.py
snib/scanner.py
snib/utils.py
snib/writer.py
snib/presets/cpp.toml
snib/presets/datascience.toml
snib/presets/java.toml
snib/presets/python.toml
snib/presets/unity.toml
snib/presets/unreal.toml
snib/presets/web.toml
snib-0.4.4.dist-info/METADATA
snib-0.4.4.dist-info/WHEEL
snib-0.4.4.dist-info/entry_points.txt
snib-0.4.4.dist-info/licenses/LICENSE
snib-0.4.4.dist-info/RECORD
