Metadata-Version: 2.4
Name: snib
Version: 0.4.4
Summary: snib scans projects and generates prompt-ready chunks
Project-URL: Homepage, https://github.com/patmllr/snib
Project-URL: Issues, https://github.com/patmllr/snib/issues
Author-email: Patrick Müller <patrick.mueller.net@protonmail.com>
License-Expression: MIT
License-File: LICENSE
Classifier: Development Status :: 4 - Beta
Classifier: Intended Audience :: Developers
Classifier: Operating System :: OS Independent
Classifier: Programming Language :: Python :: 3.9
Classifier: Topic :: Software Development :: Code Generators
Requires-Python: >=3.9
Requires-Dist: rich>=10.11.0
Requires-Dist: toml>=0.10.2
Requires-Dist: typer[all]>=0.9.0
Provides-Extra: dev
Requires-Dist: build; extra == 'dev'
Requires-Dist: hatch; extra == 'dev'
Requires-Dist: mkdocs; extra == 'dev'
Requires-Dist: mkdocs-material; extra == 'dev'
Requires-Dist: mkdocstrings; extra == 'dev'
Requires-Dist: mkdocstrings-python; extra == 'dev'
Requires-Dist: pymdown-extensions; extra == 'dev'
Requires-Dist: pytest-cov; extra == 'dev'
Requires-Dist: pytest>=8.0.0; extra == 'dev'
